youtube_related/__init__.py
youtube_related/client.py
youtube_related/error.py
youtube_related-1.0.3.dist-info/LICENSE
youtube_related-1.0.3.dist-info/METADATA
youtube_related-1.0.3.dist-info/WHEEL
youtube_related-1.0.3.dist-info/top_level.txt
youtube_related-1.0.3.dist-info/RECORD
