Metadata-Version: 2.1
Name: youtube-related
Version: 1.0.3
Summary: Youtube Related Video Fetcher
Home-page: https://github.com/kijk2869/youtube-related
Author: kijk2869
License: MIT
Project-URL: Homepage, https://youtube.com/
Project-URL: Source, https://github.com/kijk2869/youtube-related
Project-URL: Tracker, https://github.com/kijk2869/youtube-related/issues
Platform: UNKNOWN
Classifier: Programming Language :: Python :: 3.6
Classifier: Programming Language :: Python :: 3.7
Classifier: Programming Language :: Python :: 3.8
Requires-Python: >=3.6
License-File: LICENSE
Requires-Dist: aiohttp (<3.8.0,>=3.6.0)
Requires-Dist: requests (==2.25.1)
